setup.py
odoo/addons/multimedia_api_somconnexio/CHANGELOG.md
odoo/addons/multimedia_api_somconnexio/README.rst
odoo/addons/multimedia_api_somconnexio/__init__.py
odoo/addons/multimedia_api_somconnexio/__manifest__.py
odoo/addons/multimedia_api_somconnexio/models/__init__.py
odoo/addons/multimedia_api_somconnexio/models/catalog_service.py
odoo/addons/multimedia_api_somconnexio/services/__init__.py
odoo/addons/multimedia_api_somconnexio/services/contract_contract_service.py
odoo/addons/multimedia_api_somconnexio/services/crm_lead.py
odoo/addons/multimedia_api_somconnexio/services/fiber_contract_process.py
odoo/addons/multimedia_api_somconnexio/services/product_catalog_service.py
odoo/addons/multimedia_api_somconnexio/tests/__init__.py
odoo/addons/multimedia_api_somconnexio/tests/models/__init__.py
odoo/addons/multimedia_api_somconnexio/tests/models/test_catalog_service.py
odoo/addons/multimedia_api_somconnexio/tests/services/__init__.py
odoo/addons/multimedia_api_somconnexio/tests/services/test_contract_multimedia_service.py
odoo/addons/multimedia_api_somconnexio/tests/services/test_contract_search_controller.py
odoo/addons/multimedia_api_somconnexio/tests/services/test_crm_lead.py
odoo/addons/multimedia_api_somconnexio/tests/services/test_fiber_contract_process.py
odoo/addons/multimedia_api_somconnexio/tests/services/test_product_catalog_service.py
odoo_addon_multimedia_api_somconnexio.egg-info/PKG-INFO
odoo_addon_multimedia_api_somconnexio.egg-info/SOURCES.txt
odoo_addon_multimedia_api_somconnexio.egg-info/dependency_links.txt
odoo_addon_multimedia_api_somconnexio.egg-info/not-zip-safe
odoo_addon_multimedia_api_somconnexio.egg-info/requires.txt
odoo_addon_multimedia_api_somconnexio.egg-info/top_level.txt